himpunan_maths_discrete/__init__.py
himpunan_maths_discrete/himpunan.py
himpunan_maths_discrete/main.py
himpunan_maths_discrete-1.0.1.dist-info/licenses/LICENSE
himpunan_maths_discrete-1.0.1.dist-info/METADATA
himpunan_maths_discrete-1.0.1.dist-info/WHEEL
himpunan_maths_discrete-1.0.1.dist-info/top_level.txt
himpunan_maths_discrete-1.0.1.dist-info/RECORD
