Metadata-Version: 2.4
Name: himpunan-maths-discrete
Version: 1.0.1
Summary: Implementasi teori himpunan untuk Matematika Diskrit dalam Python
Home-page: https://github.com/wyattmatt/himpunan-maths-discrete
Author: Wyatt Matthew
Author-email: Wyatt Matthew <wyatt.honny06@gmail.com>
License: MIT
Project-URL: Homepage, https://github.com/wyattmatt/himpunan-maths-discrete
Project-URL: Bug Reports, https://github.com/wyattmatt/himpunan-maths-discrete/issues
Project-URL: Source, https://github.com/wyattmatt/himpunan-maths-discrete
Keywords: matematika,diskrit,himpunan,set theory,discrete mathematics
Classifier: Development Status :: 3 - Alpha
Classifier: Intended Audience :: Education
Classifier: Topic :: Education
Classifier: Topic :: Scientific/Engineering :: Mathematics
Classifier: License :: OSI Approved :: MIT License
Classifier: Programming Language :: Python :: 3
Classifier: Programming Language :: Python :: 3.7
Classifier: Programming Language :: Python :: 3.8
Classifier: Programming Language :: Python :: 3.9
Classifier: Programming Language :: Python :: 3.10
Classifier: Programming Language :: Python :: 3.11
Classifier: Programming Language :: Python :: 3.12
Requires-Python: >=3.7
License-File: LICENSE
Dynamic: author
Dynamic: home-page
Dynamic: license-file
Dynamic: requires-python
